aeolis/__init__.py
aeolis/avalanching.py
aeolis/bed.py
aeolis/console.py
aeolis/console_debug.py
aeolis/constants.py
aeolis/erosion.py
aeolis/fences.py
aeolis/gridparams.py
aeolis/hydro.py
aeolis/inout.py
aeolis/model.py
aeolis/netcdf.py
aeolis/rotation.py
aeolis/run_console.py
aeolis/shear.py
aeolis/threshold.py
aeolis/transport.py
aeolis/utils.py
aeolis/vegetation.py
aeolis/wind.py
aeolis/examples/README.md
aeolis/examples/README.txt
aeolis/examples/2D/readme.txt
aeolis/examples/2D/Barchan_dune/aeolis.txt
aeolis/examples/2D/Barchan_dune/configfile.txt
aeolis/examples/2D/Barchan_dune/ne.grd
aeolis/examples/2D/Barchan_dune/readme.txt
aeolis/examples/2D/Barchan_dune/tide.txt
aeolis/examples/2D/Barchan_dune/wave.txt
aeolis/examples/2D/Barchan_dune/wind.txt
aeolis/examples/2D/Barchan_dune/x.grd
aeolis/examples/2D/Barchan_dune/y.grd
aeolis/examples/2D/Barchan_dune/z.grd
aeolis/examples/2D/Carrara_Coast/aeolis.txt
aeolis/examples/2D/Carrara_Coast/create_vegetation_mask.py
aeolis/examples/2D/Carrara_Coast/create_xyzfile.py
aeolis/examples/2D/Carrara_Coast/grain_sample1.txt
aeolis/examples/2D/Carrara_Coast/grain_sample2.txt
aeolis/examples/2D/Carrara_Coast/plot_aeolis_results.py
aeolis/examples/2D/Carrara_Coast/street.txt
aeolis/examples/2D/Carrara_Coast/tide.txt
aeolis/examples/2D/Carrara_Coast/wind.txt
aeolis/examples/2D/Carrara_Coast/x.txt
aeolis/examples/2D/Carrara_Coast/y.txt
aeolis/examples/2D/Carrara_Coast/z.txt
aeolis/examples/2D/Parabolic_dune/aeolis.txt
aeolis/examples/2D/Parabolic_dune/ne.grd
aeolis/examples/2D/Parabolic_dune/tide.grd
aeolis/examples/2D/Parabolic_dune/tide.txt
aeolis/examples/2D/Parabolic_dune/veg.grd
aeolis/examples/2D/Parabolic_dune/wave.txt
aeolis/examples/2D/Parabolic_dune/wind.txt
aeolis/examples/2D/Parabolic_dune/x.grd
aeolis/examples/2D/Parabolic_dune/y.grd
aeolis/examples/2D/Parabolic_dune/z.grd
aeolis/examples/deVries2023/2D_Domain.PNG
aeolis/examples/deVries2023/Series of AeoLiS animations.pptx
aeolis-3.0.1.dist-info/METADATA
aeolis-3.0.1.dist-info/WHEEL
aeolis-3.0.1.dist-info/entry_points.txt
aeolis-3.0.1.dist-info/licenses/LICENSE.txt
aeolis-3.0.1.dist-info/RECORD
