Metadata-Version: 2.4
Name: aeolis
Version: 3.0.1
Summary: A process-based model for simulating supply-limited aeolian sediment transport
Project-URL: Homepage, https://github.com/openearth/aeolis-python
Project-URL: Documentation, https://aeolis-python.readthedocs.io
Project-URL: Bug Tracker, https://github.com/openearth/aeolis-python/issues
Author-email: Sierd de Vries <sierd.devries@tudelft.nl>
Maintainer: Bart van Westen
Maintainer-email: Sierd de Vries <sierd.devries@tudelft.nl>
License:                     GNU GENERAL PUBLIC LICENSE
License-File: LICENSE.txt
Keywords: aeolian sediment,deltares,model,transport,tudelft
Classifier: Development Status :: 5 - Production/Stable
Classifier: Environment :: Console
Classifier: Intended Audience :: Developers
Classifier: Intended Audience :: Science/Research
Classifier: License :: OSI Approved :: GNU General Public License v3 (GPLv3)
Classifier: Natural Language :: English
Classifier: Operating System :: MacOS :: MacOS X
Classifier: Operating System :: Microsoft :: Windows
Classifier: Operating System :: POSIX
Classifier: Operating System :: Unix
Classifier: Programming Language :: Python :: 3.9
Classifier: Programming Language :: Python :: 3.10
Classifier: Topic :: Scientific/Engineering :: Physics
Requires-Python: <4,>=3.9
Requires-Dist: bmi-python
Requires-Dist: docopt
Requires-Dist: matplotlib
Requires-Dist: netcdf4
Requires-Dist: numba
Requires-Dist: numpy
Requires-Dist: scipy
Requires-Dist: typer
Provides-Extra: dev
Requires-Dist: nbsphinx>=0.9.2; extra == 'dev'
Requires-Dist: plot==0.6.5; extra == 'dev'
Requires-Dist: pytest; extra == 'dev'
Requires-Dist: pytest-cov; extra == 'dev'
Requires-Dist: sphinx-copybutton==0.5.2; extra == 'dev'
Requires-Dist: sphinx-rtd-theme; extra == 'dev'
Requires-Dist: sphinx<7; extra == 'dev'
Requires-Dist: sphinxcontrib-bibtex>=2.5.0; extra == 'dev'
